{"config":"C28","deviceOrder":["tablet","laptop","phone"],"targetAccuracy":0.5,"keyStrokeDelay":0,"totalSuggestions":3,"suggestionsType":"BAR","numberOfPracticeTasks":3,"numberOfTypingTasks":20,"doNotShowDelayInstructions":true,"wave":"multi-device","children":[{"children":[{"task":"InformationScreen","content":"<h1>Typing on phone</h1><p>Let's start with a short tutorial</p>","key":"typing-phone-info-start"},{"task":"Tutorial","isPractice":true,"key":"typing-phone-tuto","id":"typing-phone-tuto"},{"task":"InformationScreen","content":"<h1>Practice</h1><p>Continue with the practice tasks.</p>","key":"typing-phone-info-practice-start"},{"totalKss":0.5161290322580645,"meanWordsKss":0.5837301587301588,"sdWordsKss":0.19986965077036528,"diffTotalKss":0.016129032258064502,"diffWordsMeanKss":0.08373015873015877,"diffSdWordsKss":0.00013034922963472972,"score":0.008129690743849616,"usable":true,"task":"TypingTask","sksDistribution":[{"word":"give ","sks":4,"correctSuggestionPositions":[null,1,1,1,1,1]},{"word":"me ","sks":2,"correctSuggestionPositions":[null,3,1,1]},{"word":"one ","sks":3,"correctSuggestionPositions":[null,1,1,1,1]},{"word":"spoonful ","sks":3,"correctSuggestionPositions":[null,null,null,null,null,null,2,2,2,1]},{"word":"of ","sks":2,"correctSuggestionPositions":[null,3,1,1]},{"word":"coffee ","sks":2,"correctSuggestionPositions":[null,null,null,null,null,1,1,1]}],"isPractice":true,"id":"typing-phone-practice-0","key":"typing-phone-practice-0"},{"totalKss":0.5,"meanWordsKss":0.5823443223443224,"sdWordsKss":0.2011359814223104,"diffTotalKss":0,"diffWordsMeanKss":0.08234432234432243,"diffSdWordsKss":0.0011359814223103892,"score":0.0005679907111551946,"usable":true,"task":"TypingTask","sksDistribution":[{"word":"the ","sks":2,"correctSuggestionPositions":[null,null,2,1,1]},{"word":"registration ","sks":3,"correctSuggestionPositions":[null,null,null,null,null,null,null,null,null,null,1,1,1,1]},{"word":"period ","sks":5,"correctSuggestionPositions":[null,null,2,1,1,1,1,1]},{"word":"is ","sks":2,"correctSuggestionPositions":[null,1,1,1]},{"word":"over ","sks":4,"correctSuggestionPositions":[null,1,1,1,1,1]}],"isPractice":true,"id":"typing-phone-practice-1","key":"typing-phone-practice-1"},{"totalKss":0.5217391304347826,"meanWordsKss":0.5599999999999999,"sdWordsKss":0.19136933459209765,"diffTotalKss":0.021739130434782594,"diffWordsMeanKss":0.05999999999999994,"diffSdWordsKss":0.00863066540790236,"score":0.015184897921342477,"usable":true,"task":"TypingTask","sksDistribution":[{"word":"lydia ","sks":2,"correctSuggestionPositions":[null,null,null,null,1,1,1]},{"word":"wants ","sks":2,"correctSuggestionPositions":[null,null,null,null,2,1,1]},{"word":"to ","sks":2,"correctSuggestionPositions":[null,1,1,1]},{"word":"go ","sks":2,"correctSuggestionPositions":[null,1,1,1]},{"word":"home ","sks":4,"correctSuggestionPositions":[null,1,1,1,1,1]}],"isPractice":true,"id":"typing-phone-practice-2","key":"typing-phone-practice-2"},{"task":"InformationScreen","content":"<h1>Experiment</h1><p>Practice is over. You may take a break. The real experiment begins immediately after this screen!</p><p>Remember to complete every task as fast and accurately as you can.</p>","key":"typing-phone-info-typing-start"},{"totalKss":0.5185185185185185,"meanWordsKss":0.5535714285714286,"sdWordsKss":0.19964892656248123,"diffTotalKss":0.01851851851851849,"diffWordsMeanKss":0.0535714285714286,"diffSdWordsKss":0.0003510734375187785,"score":0.009434795978018634,"usable":true,"task":"TypingTask","sksDistribution":[{"word":"the ","sks":3,"correctSuggestionPositions":[null,2,1,1,1]},{"word":"second ","sks":5,"correctSuggestionPositions":[null,null,1,1,1,1,1,1]},{"word":"largest ","sks":2,"correctSuggestionPositions":[null,null,null,null,null,null,2,1,1]},{"word":"country ","sks":4,"correctSuggestionPositions":[null,null,null,null,3,2,1,1,1]}],"id":"typing-phone-phrase-0","key":"typing-phone-phrase-0"},{"totalKss":0.5161290322580645,"meanWordsKss":0.5547619047619047,"sdWordsKss":0.2029404032129527,"diffTotalKss":0.016129032258064502,"diffWordsMeanKss":0.05476190476190468,"diffSdWordsKss":0.0029404032129526914,"score":0.009534717735508597,"usable":true,"task":"TypingTask","sksDistribution":[{"word":"the ","sks":2,"correctSuggestionPositions":[null,null,1,1,1]},{"word":"largest ","sks":4,"correctSuggestionPositions":[null,null,null,null,2,2,2,1,1]},{"word":"of ","sks":3,"correctSuggestionPositions":[1,1,1,1]},{"word":"the ","sks":2,"correctSuggestionPositions":[null,null,2,1,1]},{"word":"five ","sks":2,"correctSuggestionPositions":[null,null,null,1,1,1]},{"word":"oceans ","sks":3,"correctSuggestionPositions":[null,null,null,null,2,2,1,1]}],"id":"typing-phone-phrase-1","key":"typing-phone-phrase-1"},{"totalKss":0.5142857142857142,"meanWordsKss":0.5791666666666667,"sdWordsKss":0.19917364004528532,"diffTotalKss":0.014285714285714235,"diffWordsMeanKss":0.07916666666666672,"diffSdWordsKss":0.0008263599547146949,"score":0.007556037120214465,"usable":true,"task":"TypingTask","sksDistribution":[{"word":"I ","sks":2,"correctSuggestionPositions":[2,1,1]},{"word":"like ","sks":3,"correctSuggestionPositions":[null,null,3,1,1,1]},{"word":"baroque ","sks":3,"correctSuggestionPositions":[null,null,null,null,null,2,2,1,1]},{"word":"and ","sks":2,"correctSuggestionPositions":[null,null,2,1,1]},{"word":"classical ","sks":5,"correctSuggestionPositions":[null,null,null,null,null,2,2,2,2,2,2]},{"word":"music ","sks":3,"correctSuggestionPositions":[null,null,null,1,1,1,1]}],"id":"typing-phone-phrase-2","key":"typing-phone-phrase-2"},{"totalKss":0.5,"meanWordsKss":0.5304761904761904,"sdWordsKss":0.18387612906248127,"diffTotalKss":0,"diffWordsMeanKss":0.030476190476190435,"diffSdWordsKss":0.01612387093751874,"score":0.00806193546875937,"usable":true,"task":"TypingTask","sksDistribution":[{"word":"hair ","sks":4,"correctSuggestionPositions":[null,3,1,1,1,1]},{"word":"gel ","sks":2,"correctSuggestionPositions":[null,null,1,1,1]},{"word":"is ","sks":2,"correctSuggestionPositions":[null,2,2,1]},{"word":"very ","sks":2,"correctSuggestionPositions":[null,null,null,3,3,1]},{"word":"greasy ","sks":2,"correctSuggestionPositions":[null,null,null,null,null,3,3,1]}],"id":"typing-phone-phrase-3","key":"typing-phone-phrase-3"},{"totalKss":0.5,"meanWordsKss":0.5481481481481482,"sdWordsKss":0.19996570350656429,"diffTotalKss":0,"diffWordsMeanKss":0.04814814814814816,"diffSdWordsKss":0.00003429649343572594,"score":0.00001714824671786297,"usable":true,"task":"TypingTask","sksDistribution":[{"word":"in ","sks":2,"correctSuggestionPositions":[null,1,1,1]},{"word":"sharp ","sks":5,"correctSuggestionPositions":[null,2,2,1,1,1,1]},{"word":"contrast ","sks":2,"correctSuggestionPositions":[null,null,null,null,null,null,null,2,2,1]},{"word":"to ","sks":2,"correctSuggestionPositions":[null,1,1,1]},{"word":"your ","sks":2,"correctSuggestionPositions":[null,null,null,1,1,1]},{"word":"words ","sks":3,"correctSuggestionPositions":[null,null,null,2,1,1,1]}],"id":"typing-phone-phrase-4","key":"typing-phone-phrase-4"},{"totalKss":0.5151515151515151,"meanWordsKss":0.569047619047619,"sdWordsKss":0.19954596990244725,"diffTotalKss":0.015151515151515138,"diffWordsMeanKss":0.06904761904761902,"diffSdWordsKss":0.0004540300975527656,"score":0.007802772624533952,"usable":true,"task":"TypingTask","sksDistribution":[{"word":"our ","sks":2,"correctSuggestionPositions":[null,null,1,1,1]},{"word":"silver ","sks":4,"correctSuggestionPositions":[null,null,null,1,1,1,1,1]},{"word":"anniversary ","sks":3,"correctSuggestionPositions":[null,null,null,null,null,null,null,null,null,2,1,1,1]},{"word":"is ","sks":2,"correctSuggestionPositions":[null,1,1,1]},{"word":"coming ","sks":6,"correctSuggestionPositions":[null,1,1,1,1,1,1,1]}],"id":"typing-phone-phrase-5","key":"typing-phone-phrase-5"},{"totalKss":0.5,"meanWordsKss":0.5533333333333333,"sdWordsKss":0.20176994600562073,"diffTotalKss":0,"diffWordsMeanKss":0.053333333333333344,"diffSdWordsKss":0.0017699460056207206,"score":0.0008849730028103603,"usable":true,"task":"TypingTask","sksDistribution":[{"word":"head ","sks":3,"correctSuggestionPositions":[null,null,3,3,1,1]},{"word":"shoulders ","sks":2,"correctSuggestionPositions":[null,null,null,null,null,null,null,null,2,2,2]},{"word":"knees ","sks":4,"correctSuggestionPositions":[null,null,2,1,1,1,1]},{"word":"and ","sks":2,"correctSuggestionPositions":[null,null,1,1,1]},{"word":"toes ","sks":4,"correctSuggestionPositions":[null,2,1,1,1,1]}],"id":"typing-phone-phrase-6","key":"typing-phone-phrase-6"},{"totalKss":0.48484848484848486,"meanWordsKss":0.5435064935064935,"sdWordsKss":0.20263069989446322,"diffTotalKss":0.015151515151515138,"diffWordsMeanKss":0.04350649350649349,"diffSdWordsKss":0.002630699894463212,"score":0.008891107522989175,"usable":true,"task":"TypingTask","sksDistribution":[{"word":"the ","sks":2,"correctSuggestionPositions":[null,null,1,1,1]},{"word":"acceptance ","sks":2,"correctSuggestionPositions":[null,null,null,null,null,null,null,null,null,3,1,1]},{"word":"speech ","sks":4,"correctSuggestionPositions":[null,null,null,1,1,1,1,1]},{"word":"was ","sks":3,"correctSuggestionPositions":[null,2,1,1,1]},{"word":"boring ","sks":5,"correctSuggestionPositions":[null,null,2,2,1,1,1,1]}],"id":"typing-phone-phrase-7","key":"typing-phone-phrase-7"},{"totalKss":0.5,"meanWordsKss":0.5596590909090909,"sdWordsKss":0.1992938168250625,"diffTotalKss":0,"diffWordsMeanKss":0.05965909090909094,"diffSdWordsKss":0.000706183174937508,"score":0.000353091587468754,"usable":true,"task":"TypingTask","sksDistribution":[{"word":"world ","sks":5,"correctSuggestionPositions":[null,1,1,1,1,1,1]},{"word":"population ","sks":4,"correctSuggestionPositions":[null,null,null,null,null,null,null,3,1,1,1,1]},{"word":"is ","sks":2,"correctSuggestionPositions":[null,3,1,1]},{"word":"growing ","sks":3,"correctSuggestionPositions":[null,null,null,null,null,3,1,1,1]}],"id":"typing-phone-phrase-8","key":"typing-phone-phrase-8"},{"totalKss":0.4827586206896552,"meanWordsKss":0.5413961038961039,"sdWordsKss":0.19894644446065168,"diffTotalKss":0.017241379310344807,"diffWordsMeanKss":0.04139610389610393,"diffSdWordsKss":0.0010535555393483276,"score":0.009147467424846567,"usable":true,"task":"TypingTask","sksDistribution":[{"word":"please ","sks":5,"correctSuggestionPositions":[null,null,3,2,2,1,1,1]},{"word":"follow ","sks":3,"correctSuggestionPositions":[null,null,null,null,1,1,1,1]},{"word":"the ","sks":3,"correctSuggestionPositions":[null,3,1,1,1]},{"word":"guidelines ","sks":3,"correctSuggestionPositions":[null,null,null,null,null,null,null,null,3,1,1,1]}],"id":"typing-phone-phrase-9","key":"typing-phone-phrase-9"},{"totalKss":0.5128205128205128,"meanWordsKss":0.5444444444444444,"sdWordsKss":0.20038543107634924,"diffTotalKss":0.012820512820512775,"diffWordsMeanKss":0.0444444444444444,"diffSdWordsKss":0.00038543107634922413,"score":0.0066029719484309995,"usable":true,"task":"TypingTask","sksDistribution":[{"word":"did ","sks":2,"correctSuggestionPositions":[null,null,1,1,1]},{"word":"you ","sks":3,"correctSuggestionPositions":[null,1,1,1,1]},{"word":"see ","sks":3,"correctSuggestionPositions":[null,2,1,1,1]},{"word":"that ","sks":2,"correctSuggestionPositions":[null,null,null,1,1,1]},{"word":"spectacular ","sks":8,"correctSuggestionPositions":[null,null,null,null,3,2,1,1,1,1,1,1,1]},{"word":"explosion ","sks":2,"correctSuggestionPositions":[null,null,null,null,null,null,null,null,1,1,1]}],"id":"typing-phone-phrase-10","key":"typing-phone-phrase-10"},{"totalKss":0.5185185185185185,"meanWordsKss":0.5347222222222222,"sdWordsKss":0.201628210291083,"diffTotalKss":0.01851851851851849,"diffWordsMeanKss":0.03472222222222221,"diffSdWordsKss":0.001628210291082982,"score":0.010073364404800736,"usable":true,"task":"TypingTask","sksDistribution":[{"word":"olympic ","sks":6,"correctSuggestionPositions":[null,null,2,2,1,1,1,1,1]},{"word":"athletes ","sks":2,"correctSuggestionPositions":[null,null,null,null,null,null,null,2,2,1]},{"word":"use ","sks":2,"correctSuggestionPositions":[null,null,3,1,1]},{"word":"drugs ","sks":4,"correctSuggestionPositions":[null,null,3,3,1,1,1]}],"id":"typing-phone-phrase-11","key":"typing-phone-phrase-11"},{"totalKss":0.5161290322580645,"meanWordsKss":0.5802721088435374,"sdWordsKss":0.20197323590889146,"diffTotalKss":0.016129032258064502,"diffWordsMeanKss":0.08027210884353742,"diffSdWordsKss":0.001973235908891452,"score":0.009051134083477977,"usable":true,"task":"TypingTask","sksDistribution":[{"word":"he ","sks":2,"correctSuggestionPositions":[null,3,1,1]},{"word":"played ","sks":3,"correctSuggestionPositions":[null,null,null,null,3,3,2,2]},{"word":"a ","sks":2,"correctSuggestionPositions":[2,1,1]},{"word":"pimp ","sks":2,"correctSuggestionPositions":[null,null,null,3,1,1]},{"word":"in ","sks":2,"correctSuggestionPositions":[null,2,1,1]},{"word":"that ","sks":2,"correctSuggestionPositions":[null,null,null,1,1,1]},{"word":"movie ","sks":3,"correctSuggestionPositions":[null,null,null,2,1,1,1]}],"id":"typing-phone-phrase-12","key":"typing-phone-phrase-12"},{"totalKss":0.5121951219512195,"meanWordsKss":0.4666666666666667,"sdWordsKss":0.2,"diffTotalKss":0.012195121951219523,"diffWordsMeanKss":0.033333333333333326,"diffSdWordsKss":0,"score":0.0060975609756097615,"usable":true,"task":"TypingTask","sksDistribution":[{"word":"irregular ","sks":6,"correctSuggestionPositions":[null,null,null,null,3,2,1,1,2,2,2]},{"word":"verbs ","sks":3,"correctSuggestionPositions":[null,null,null,3,1,1,1]},{"word":"are ","sks":2,"correctSuggestionPositions":[null,null,1,1,1]},{"word":"the ","sks":2,"correctSuggestionPositions":[null,null,1,1,1]},{"word":"hardest ","sks":4,"correctSuggestionPositions":[null,null,null,null,2,1,1,1,1]},{"word":"to ","sks":0,"correctSuggestionPositions":[null,null,null,1]},{"word":"learn ","sks":4,"correctSuggestionPositions":[null,null,1,1,1,1,1]}],"id":"typing-phone-phrase-13","key":"typing-phone-phrase-13"},{"totalKss":0.4838709677419355,"meanWordsKss":0.38095238095238093,"sdWordsKss":0.24743582965269673,"diffTotalKss":0.016129032258064502,"diffWordsMeanKss":0.11904761904761907,"diffSdWordsKss":0.047435829652696715,"score":0.03178243095538061,"usable":true,"task":"TypingTask","sksDistribution":[{"word":"pay ","sks":2,"correctSuggestionPositions":[null,null,1,1,1]},{"word":"off ","sks":2,"correctSuggestionPositions":[null,null,1,1,1]},{"word":"a ","sks":0,"correctSuggestionPositions":[null,null,1]},{"word":"mortgage ","sks":6,"correctSuggestionPositions":[null,null,null,3,1,1,1,1,1,1]},{"word":"for ","sks":2,"correctSuggestionPositions":[null,null,1,1,1]},{"word":"a ","sks":0,"correctSuggestionPositions":[null,null,2]},{"word":"house ","sks":3,"correctSuggestionPositions":[null,null,null,2,1,1,1]}],"id":"typing-phone-phrase-14","key":"typing-phone-phrase-14"},{"totalKss":0.5,"meanWordsKss":0.5427777777777778,"sdWordsKss":0.2056276149970687,"diffTotalKss":0,"diffWordsMeanKss":0.0427777777777778,"diffSdWordsKss":0.005627614997068681,"score":0.0028138074985343403,"usable":true,"task":"TypingTask","sksDistribution":[{"word":"express ","sks":5,"correctSuggestionPositions":[null,null,null,1,1,1,1,1,1]},{"word":"delivery ","sks":2,"correctSuggestionPositions":[null,null,null,null,null,null,null,1,1,1]},{"word":"is ","sks":2,"correctSuggestionPositions":[null,2,2,1]},{"word":"very ","sks":4,"correctSuggestionPositions":[null,3,1,1,1,1]},{"word":"fast ","sks":2,"correctSuggestionPositions":[null,null,null,3,2,1]}],"id":"typing-phone-phrase-15","key":"typing-phone-phrase-15"},{"totalKss":0.5,"meanWordsKss":0.5847222222222221,"sdWordsKss":0.22290260426395722,"diffTotalKss":0,"diffWordsMeanKss":0.08472222222222214,"diffSdWordsKss":0.02290260426395721,"score":0.011451302131978605,"usable":true,"task":"TypingTask","sksDistribution":[{"word":"do ","sks":2,"correctSuggestionPositions":[null,2,1,1]},{"word":"a ","sks":2,"correctSuggestionPositions":[2,1,1]},{"word":"good ","sks":2,"correctSuggestionPositions":[null,null,null,2,2,2]},{"word":"deed ","sks":2,"correctSuggestionPositions":[null,null,null,2,1,1]},{"word":"to ","sks":2,"correctSuggestionPositions":[null,1,1,1]},{"word":"someone ","sks":3,"correctSuggestionPositions":[null,null,null,null,null,2,2,2,2]}],"id":"typing-phone-phrase-16","key":"typing-phone-phrase-16"},{"totalKss":0.5,"meanWordsKss":0.5708333333333333,"sdWordsKss":0.20628156324144273,"diffTotalKss":0,"diffWordsMeanKss":0.0708333333333333,"diffSdWordsKss":0.006281563241442717,"score":0.0031407816207213585,"usable":true,"task":"TypingTask","sksDistribution":[{"word":"for ","sks":3,"correctSuggestionPositions":[null,1,1,1,1]},{"word":"your ","sks":4,"correctSuggestionPositions":[null,3,1,1,1,1]},{"word":"information ","sks":4,"correctSuggestionPositions":[null,null,null,null,null,null,null,null,1,1,1,1,1]},{"word":"only ","sks":2,"correctSuggestionPositions":[null,null,null,1,1,1]}],"id":"typing-phone-phrase-17","key":"typing-phone-phrase-17"},{"totalKss":0.5,"meanWordsKss":0.44186507936507935,"sdWordsKss":0.20010223121006965,"diffTotalKss":0,"diffWordsMeanKss":0.05813492063492065,"diffSdWordsKss":0.00010223121006963654,"score":0.00005111560503481827,"usable":true,"task":"TypingTask","sksDistribution":[{"word":"for ","sks":2,"correctSuggestionPositions":[null,null,2,1,1]},{"word":"murder ","sks":3,"correctSuggestionPositions":[null,null,null,null,2,2,2,2]},{"word":"you ","sks":2,"correctSuggestionPositions":[null,null,2,1,1]},{"word":"get ","sks":2,"correctSuggestionPositions":[null,null,2,1,1]},{"word":"a ","sks":0,"correctSuggestionPositions":[null,null,2]},{"word":"long ","sks":2,"correctSuggestionPositions":[null,null,null,3,2,2]},{"word":"prison ","sks":3,"correctSuggestionPositions":[null,null,null,null,1,1,1,1]},{"word":"sentence ","sks":7,"correctSuggestionPositions":[null,null,1,1,1,1,1,1,1,1]}],"id":"typing-phone-phrase-18","key":"typing-phone-phrase-18"},{"totalKss":0.5185185185185185,"meanWordsKss":0.5333333333333333,"sdWordsKss":0.21343747458109494,"diffTotalKss":0.01851851851851849,"diffWordsMeanKss":0.033333333333333326,"diffSdWordsKss":0.013437474581094927,"score":0.01597799654980671,"usable":true,"task":"TypingTask","sksDistribution":[{"word":"are ","sks":2,"correctSuggestionPositions":[null,null,1,1,1]},{"word":"you ","sks":2,"correctSuggestionPositions":[null,null,1,1,1]},{"word":"sure ","sks":2,"correctSuggestionPositions":[null,null,null,1,1,1]},{"word":"you ","sks":4,"correctSuggestionPositions":[1,1,1,1,1]},{"word":"want ","sks":2,"correctSuggestionPositions":[null,null,null,3,2,2]},{"word":"this ","sks":2,"correctSuggestionPositions":[null,null,null,2,2,1]}],"id":"typing-phone-phrase-19","key":"typing-phone-phrase-19"},{"task":"BlockQuestionnaire"},{"task":"S3Upload","key":"init-upload"},{"task":"InformationScreen","content":"Now switch to the laptop.","key":"typing-phone-info-typing-end"}],"isVirtualKeyboardEnabled":true}],"device":"phone"}